{"name":"flag11Trigger","class":"BeamNGTrigger","luaFunction":"Transporter.onCTFTrigger","persistentId":"48976733-56e4-4f7c-a3f5-32653e3ae965","__parent":"SimGroup_8","position":[-1869.71521,3784.70947,91.7295837],"scale":[2,2,35],"triggerMode":"Overlaps","triggerTestType":"Bounding box"}
{"name":"SimGroup_8","class":"SimGroup","persistentId":"cd659b20-ca34-4238-b806-c7035304d355","groupPosition":"0 0 0"}
{"name":"flag11TSStatic","class":"TSStatic","persistentId":"a639717e-3319-4f25-acfa-33397a843af5","__parent":"SimGroup_8","position":[-1869.71521,3784.70947,225.729584],"annotation":"OBSTACLES","collisionType":"None","decalType":"None","instanceColor":[0,0.0227570534,1,1],"instanceColor1":[0,0.0238099098,1,1],"isRenderEnabled":false,"rotationMatrix":[1,1.34110451e-07,-1.74845553e-07,1.34110394e-07,-1,-3.2584137e-07,-1.7484561e-07,3.25841341e-07,-1],"scale":[10,10,6],"shapeName":"/art/shapes/interface/single_faded_column.dae","useInstanceRenderData":true}
